queue_core.py
task_queue.py
tq.py
agent_task_queue-0.3.0.dist-info/METADATA
agent_task_queue-0.3.0.dist-info/WHEEL
agent_task_queue-0.3.0.dist-info/entry_points.txt
agent_task_queue-0.3.0.dist-info/licenses/LICENSE
agent_task_queue-0.3.0.dist-info/RECORD
