Metadata-Version: 2.4
Name: agent-task-queue
Version: 0.3.0
Summary: MCP server for sequential task execution via FIFO queue
Author-email: Matt McKenna <mmckenna@block.xyz>, Block <opensource@block.xyz>
License-Expression: Apache-2.0
License-File: LICENSE
Requires-Python: >=3.10
Requires-Dist: fastmcp>=2.3.0
Provides-Extra: dev
Requires-Dist: pytest-asyncio>=0.24; extra == 'dev'
Requires-Dist: pytest>=8.0; extra == 'dev'
Requires-Dist: ruff>=0.8; extra == 'dev'
